{"metadata": {"dbt_schema_version": "https://schemas.getdbt.com/dbt/run-results/v5.json", "dbt_version": "1.7.9", "generated_at": "2024-07-02T20:46:50.193344Z", "invocation_id": "481623ac-d781-4533-bbf6-824a67dc72a6", "env": {}}, "results": [{"status": "success", "timing": [{"name": "compile", "started_at": "2024-07-02T20:46:46.927303Z", "completed_at": "2024-07-02T20:46:47.654810Z"}, {"name": "execute", "started_at": "2024-07-02T20:46:47.655860Z", "completed_at": "2024-07-02T20:46:47.655891Z"}], "thread_id": "Thread-4 (worker)", "execution_time": 0.7600159645080566, "adapter_response": {}, "message": null, "failures": null, "unique_id": "model.twilio_source.stg_twilio__incoming_phone_number_tmp", "compiled": true, "compiled_code": "select `id`,\n  `_fivetran_synced`,\n  `account_id`,\n  `address_id`,\n  `address_requirements`,\n  `beta`,\n  `capabilities_mms`,\n  `capabilities_sms`,\n  `capabilities_voice`,\n  `created_at`,\n  `emergency_address_id`,\n  `emergency_status`,\n  `friendly_name`,\n  `origin`,\n  `phone_number`,\n  `trunk_id`,\n  `updated_at`,\n  `voice_caller_id_lookup`,\n  `voice_url`\nfrom `dbt-package-testing`.`twilio_source_integration_tests_1`.`twilio_incoming_phone_number_data`", "relation_name": "`dbt-package-testing`.`twilio_source_integration_tests_1_twilio_source`.`stg_twilio__incoming_phone_number_tmp`"}, {"status": "success", "timing": [{"name": "compile", "started_at": "2024-07-02T20:46:46.922102Z", "completed_at": "2024-07-02T20:46:47.687329Z"}, {"name": "execute", "started_at": "2024-07-02T20:46:47.688076Z", "completed_at": "2024-07-02T20:46:47.688087Z"}], "thread_id": "Thread-2 (worker)", "execution_time": 0.7938141822814941, "adapter_response": {}, "message": null, "failures": null, "unique_id": "model.twilio_source.stg_twilio__address_tmp", "compiled": true, "compiled_code": "select `id`,\n  `_fivetran_synced`,\n  `account_id`,\n  `city`,\n  `created_at`,\n  `customer_name`,\n  `emergency_enabled`,\n  `friendly_name`,\n  `iso_country`,\n  `postal_code`,\n  `region`,\n  `street`,\n  `updated_at`,\n  `validated`,\n  `verified`\nfrom `dbt-package-testing`.`twilio_source_integration_tests_1`.`twilio_address_data`", "relation_name": "`dbt-package-testing`.`twilio_source_integration_tests_1_twilio_source`.`stg_twilio__address_tmp`"}, {"status": "success", "timing": [{"name": "compile", "started_at": "2024-07-02T20:46:46.899272Z", "completed_at": "2024-07-02T20:46:47.724452Z"}, {"name": "execute", "started_at": "2024-07-02T20:46:47.725252Z", "completed_at": "2024-07-02T20:46:47.725261Z"}], "thread_id": "Thread-1 (worker)", "execution_time": 0.832463264465332, "adapter_response": {}, "message": null, "failures": null, "unique_id": "model.twilio_source.stg_twilio__account_history_tmp", "compiled": true, "compiled_code": "select `id`,\n  `updated_at`,\n  `_fivetran_synced`,\n  `created_at`,\n  `friendly_name`,\n  `owner_account_id`,\n  `status`,\n  `type`\nfrom `dbt-package-testing`.`twilio_source_integration_tests_1`.`twilio_account_history_data`", "relation_name": "`dbt-package-testing`.`twilio_source_integration_tests_1_twilio_source`.`stg_twilio__account_history_tmp`"}, {"status": "success", "timing": [{"name": "compile", "started_at": "2024-07-02T20:46:46.924840Z", "completed_at": "2024-07-02T20:46:47.733413Z"}, {"name": "execute", "started_at": "2024-07-02T20:46:47.733936Z", "completed_at": "2024-07-02T20:46:47.733941Z"}], "thread_id": "Thread-3 (worker)", "execution_time": 0.8385767936706543, "adapter_response": {}, "message": null, "failures": null, "unique_id": "model.twilio_source.stg_twilio__call_tmp", "compiled": true, "compiled_code": "--To disable this model, set the using_twilio_call variable within your dbt_project.yml file to False.\n\n\nselect `id`,\n  `_fivetran_synced`,\n  `account_id`,\n  `annotation`,\n  `answered_by`,\n  `caller_name`,\n  `created_at`,\n  `direction`,\n  `duration`,\n  `end_time`,\n  `forwarded_from`,\n  `from`,\n  `from_formatted`,\n  `group_id`,\n  `outgoing_caller_id`,\n  `parent_call_id`,\n  `price`,\n  `price_unit`,\n  `queue_time`,\n  `start_time`,\n  `status`,\n  `to`,\n  `to_formatted`,\n  `trunk_id`,\n  `updated_at`\nfrom `dbt-package-testing`.`twilio_source_integration_tests_1`.`twilio_call_data`", "relation_name": "`dbt-package-testing`.`twilio_source_integration_tests_1_twilio_source`.`stg_twilio__call_tmp`"}, {"status": "success", "timing": [{"name": "compile", "started_at": "2024-07-02T20:46:47.659011Z", "completed_at": "2024-07-02T20:46:48.380281Z"}, {"name": "execute", "started_at": "2024-07-02T20:46:48.381018Z", "completed_at": "2024-07-02T20:46:48.381027Z"}], "thread_id": "Thread-4 (worker)", "execution_time": 0.7238771915435791, "adapter_response": {}, "message": null, "failures": null, "unique_id": "model.twilio_source.stg_twilio__message_tmp", "compiled": true, "compiled_code": "select `id`,\n  `_fivetran_synced`,\n  `account_id`,\n  `body`,\n  `created_at`,\n  `date_sent`,\n  `direction`,\n  `error_code`,\n  `error_message`,\n  `from`,\n  `messaging_service_sid`,\n  `num_media`,\n  `num_segments`,\n  `price`,\n  `price_unit`,\n  `status`,\n  `to`,\n  `updated_at`\nfrom `dbt-package-testing`.`twilio_source_integration_tests_1`.`twilio_message_data`", "relation_name": "`dbt-package-testing`.`twilio_source_integration_tests_1_twilio_source`.`stg_twilio__message_tmp`"}, {"status": "success", "timing": [{"name": "compile", "started_at": "2024-07-02T20:46:48.383583Z", "completed_at": "2024-07-02T20:46:48.385122Z"}, {"name": "execute", "started_at": "2024-07-02T20:46:48.385783Z", "completed_at": "2024-07-02T20:46:48.385788Z"}], "thread_id": "Thread-4 (worker)", "execution_time": 0.003758668899536133, "adapter_response": {}, "message": null, "failures": null, "unique_id": "seed.twilio_source_integration_tests.twilio_account_history_data", "compiled": null, "compiled_code": null, "relation_name": null}, {"status": "success", "timing": [{"name": "compile", "started_at": "2024-07-02T20:46:48.387663Z", "completed_at": "2024-07-02T20:46:48.388724Z"}, {"name": "execute", "started_at": "2024-07-02T20:46:48.389278Z", "completed_at": "2024-07-02T20:46:48.389283Z"}], "thread_id": "Thread-4 (worker)", "execution_time": 0.002788066864013672, "adapter_response": {}, "message": null, "failures": null, "unique_id": "seed.twilio_source_integration_tests.twilio_address_data", "compiled": null, "compiled_code": null, "relation_name": null}, {"status": "success", "timing": [{"name": "compile", "started_at": "2024-07-02T20:46:48.391106Z", "completed_at": "2024-07-02T20:46:48.392167Z"}, {"name": "execute", "started_at": "2024-07-02T20:46:48.392740Z", "completed_at": "2024-07-02T20:46:48.392745Z"}], "thread_id": "Thread-4 (worker)", "execution_time": 0.0028238296508789062, "adapter_response": {}, "message": null, "failures": null, "unique_id": "seed.twilio_source_integration_tests.twilio_call_data", "compiled": null, "compiled_code": null, "relation_name": null}, {"status": "success", "timing": [{"name": "compile", "started_at": "2024-07-02T20:46:48.394432Z", "completed_at": "2024-07-02T20:46:48.395315Z"}, {"name": "execute", "started_at": "2024-07-02T20:46:48.395850Z", "completed_at": "2024-07-02T20:46:48.395854Z"}], "thread_id": "Thread-4 (worker)", "execution_time": 0.002454996109008789, "adapter_response": {}, "message": null, "failures": null, "unique_id": "seed.twilio_source_integration_tests.twilio_incoming_phone_number_data", "compiled": null, "compiled_code": null, "relation_name": null}, {"status": "success", "timing": [{"name": "compile", "started_at": "2024-07-02T20:46:48.397483Z", "completed_at": "2024-07-02T20:46:48.398358Z"}, {"name": "execute", "started_at": "2024-07-02T20:46:48.398839Z", "completed_at": "2024-07-02T20:46:48.398844Z"}], "thread_id": "Thread-4 (worker)", "execution_time": 0.0024290084838867188, "adapter_response": {}, "message": null, "failures": null, "unique_id": "seed.twilio_source_integration_tests.twilio_message_data", "compiled": null, "compiled_code": null, "relation_name": null}, {"status": "success", "timing": [{"name": "compile", "started_at": "2024-07-02T20:46:48.400342Z", "completed_at": "2024-07-02T20:46:48.401158Z"}, {"name": "execute", "started_at": "2024-07-02T20:46:48.401603Z", "completed_at": "2024-07-02T20:46:48.401607Z"}], "thread_id": "Thread-4 (worker)", "execution_time": 0.0022258758544921875, "adapter_response": {}, "message": null, "failures": null, "unique_id": "seed.twilio_source_integration_tests.twilio_messaging_service_data", "compiled": null, "compiled_code": null, "relation_name": null}, {"status": "success", "timing": [{"name": "compile", "started_at": "2024-07-02T20:46:48.403294Z", "completed_at": "2024-07-02T20:46:48.405126Z"}, {"name": "execute", "started_at": "2024-07-02T20:46:48.406712Z", "completed_at": "2024-07-02T20:46:48.406716Z"}], "thread_id": "Thread-4 (worker)", "execution_time": 0.0045719146728515625, "adapter_response": {}, "message": null, "failures": null, "unique_id": "seed.twilio_source_integration_tests.twilio_outgoing_caller_id_data", "compiled": null, "compiled_code": null, "relation_name": null}, {"status": "success", "timing": [{"name": "compile", "started_at": "2024-07-02T20:46:47.690794Z", "completed_at": "2024-07-02T20:46:48.408139Z"}, {"name": "execute", "started_at": "2024-07-02T20:46:48.410871Z", "completed_at": "2024-07-02T20:46:48.410875Z"}], "thread_id": "Thread-2 (worker)", "execution_time": 0.7217638492584229, "adapter_response": {}, "message": null, "failures": null, "unique_id": "model.twilio_source.stg_twilio__messaging_service_tmp", "compiled": true, "compiled_code": "--To disable this model, set the using_twilio_messaging_service variable within your dbt_project.yml file to False.\n\n\nselect `id`,\n  `_fivetran_deleted`,\n  `_fivetran_synced`,\n  `account_id`,\n  `area_code_geomatch`,\n  `created_at`,\n  `fallback_method`,\n  `fallback_to_long_code`,\n  `fallback_url`,\n  `friendly_name`,\n  `inbound_method`,\n  `inbound_request_url`,\n  `mms_converter`,\n  `scan_message_content`,\n  `smart_encoding`,\n  `status_callback`,\n  `sticky_sender`,\n  `synchronous_validation`,\n  `updated_at`,\n  `us_app_to_person_registered`,\n  `use_inbound_webhook_on_number`,\n  `usecase`,\n  `validity_period`\nfrom `dbt-package-testing`.`twilio_source_integration_tests_1`.`twilio_messaging_service_data`", "relation_name": "`dbt-package-testing`.`twilio_source_integration_tests_1_twilio_source`.`stg_twilio__messaging_service_tmp`"}, {"status": "success", "timing": [{"name": "compile", "started_at": "2024-07-02T20:46:48.408369Z", "completed_at": "2024-07-02T20:46:48.409179Z"}, {"name": "execute", "started_at": "2024-07-02T20:46:48.411107Z", "completed_at": "2024-07-02T20:46:48.411111Z"}], "thread_id": "Thread-4 (worker)", "execution_time": 0.0043179988861083984, "adapter_response": {}, "message": null, "failures": null, "unique_id": "seed.twilio_source_integration_tests.twilio_usage_record_data", "compiled": null, "compiled_code": null, "relation_name": null}, {"status": "success", "timing": [{"name": "compile", "started_at": "2024-07-02T20:46:47.727609Z", "completed_at": "2024-07-02T20:46:48.412413Z"}, {"name": "execute", "started_at": "2024-07-02T20:46:48.413840Z", "completed_at": "2024-07-02T20:46:48.413844Z"}], "thread_id": "Thread-1 (worker)", "execution_time": 0.68955397605896, "adapter_response": {}, "message": null, "failures": null, "unique_id": "model.twilio_source.stg_twilio__outgoing_caller_id_tmp", "compiled": true, "compiled_code": "select `id`,\n  `_fivetran_synced`,\n  `created_at`,\n  `friendly_name`,\n  `phone_number`,\n  `updated_at`\nfrom `dbt-package-testing`.`twilio_source_integration_tests_1`.`twilio_outgoing_caller_id_data`", "relation_name": "`dbt-package-testing`.`twilio_source_integration_tests_1_twilio_source`.`stg_twilio__outgoing_caller_id_tmp`"}, {"status": "success", "timing": [{"name": "compile", "started_at": "2024-07-02T20:46:47.735851Z", "completed_at": "2024-07-02T20:46:48.423466Z"}, {"name": "execute", "started_at": "2024-07-02T20:46:48.423809Z", "completed_at": "2024-07-02T20:46:48.423812Z"}], "thread_id": "Thread-3 (worker)", "execution_time": 0.6890051364898682, "adapter_response": {}, "message": null, "failures": null, "unique_id": "model.twilio_source.stg_twilio__usage_record_tmp", "compiled": true, "compiled_code": "select `account_id`,\n  `category`,\n  `end_date`,\n  `start_date`,\n  `_fivetran_synced`,\n  `as_of`,\n  `count`,\n  `count_unit`,\n  `description`,\n  `price`,\n  `price_unit`,\n  `usage`,\n  `usage_unit`\nfrom `dbt-package-testing`.`twilio_source_integration_tests_1`.`twilio_usage_record_data`", "relation_name": "`dbt-package-testing`.`twilio_source_integration_tests_1_twilio_source`.`stg_twilio__usage_record_tmp`"}, {"status": "success", "timing": [{"name": "compile", "started_at": "2024-07-02T20:46:48.425039Z", "completed_at": "2024-07-02T20:46:49.259023Z"}, {"name": "execute", "started_at": "2024-07-02T20:46:49.262011Z", "completed_at": "2024-07-02T20:46:49.262016Z"}], "thread_id": "Thread-3 (worker)", "execution_time": 0.8428637981414795, "adapter_response": {}, "message": null, "failures": null, "unique_id": "model.twilio_source.stg_twilio__call", "compiled": true, "compiled_code": "--To disable this model, set the using_twilio_call variable within your dbt_project.yml file to False.\n\n\nwith base as (\n\n    select * \n    from `dbt-package-testing`.`twilio_source_integration_tests_1_twilio_source`.`stg_twilio__call_tmp`\n),\n\nfields as (\n\n    select\n        \n    \n    \n    _fivetran_synced\n    \n as \n    \n    _fivetran_synced\n    \n, \n    \n    \n    account_id\n    \n as \n    \n    account_id\n    \n, \n    \n    \n    annotation\n    \n as \n    \n    annotation\n    \n, \n    \n    \n    answered_by\n    \n as \n    \n    answered_by\n    \n, \n    \n    \n    caller_name\n    \n as \n    \n    caller_name\n    \n, \n    \n    \n    created_at\n    \n as \n    \n    created_at\n    \n, \n    \n    \n    direction\n    \n as \n    \n    direction\n    \n, \n    \n    \n    duration\n    \n as \n    \n    duration\n    \n, \n    \n    \n    end_time\n    \n as \n    \n    end_time\n    \n, \n    \n    \n    forwarded_from\n    \n as \n    \n    forwarded_from\n    \n, \n    \n    \n    from_formatted\n    \n as \n    \n    from_formatted\n    \n, \n    \n    \n    group_id\n    \n as \n    \n    group_id\n    \n, \n    \n    \n    id\n    \n as \n    \n    id\n    \n, \n    \n    \n    outgoing_caller_id\n    \n as \n    \n    outgoing_caller_id\n    \n, \n    \n    \n    parent_call_id\n    \n as \n    \n    parent_call_id\n    \n, \n    \n    \n    price\n    \n as \n    \n    price\n    \n, \n    \n    \n    price_unit\n    \n as \n    \n    price_unit\n    \n, \n    \n    \n    queue_time\n    \n as \n    \n    queue_time\n    \n, \n    \n    \n    start_time\n    \n as \n    \n    start_time\n    \n, \n    \n    \n    status\n    \n as \n    \n    status\n    \n, \n    \n    \n    to_formatted\n    \n as \n    \n    to_formatted\n    \n, \n    \n    \n    trunk_id\n    \n as \n    \n    trunk_id\n    \n, \n    \n    \n    updated_at\n    \n as \n    \n    updated_at\n    \n, \n    \n    \n        \n            \n            `from`\n            \n        \n    \n as call_from , \n    \n    \n        \n            \n            `to`\n            \n        \n    \n as call_to \n\n\n    from base\n),\n\nfinal as (\n    \n    select \n        _fivetran_synced,\n        account_id,\n        annotation,\n        answered_by,\n        caller_name,\n        created_at,\n        direction,\n        cast(duration as FLOAT64) as duration,\n        end_time,\n        forwarded_from,\n        call_from, -- renamed in the get_call_columns macro\n        from_formatted,\n        group_id,\n        id as call_id,\n        outgoing_caller_id,\n        parent_call_id,\n        cast(price as FLOAT64) as price,\n        price_unit,\n        cast(queue_time as FLOAT64) as queue_time,\n        start_time,\n        status,\n        call_to, -- renamed in the get_call_columns macro\n        to_formatted,\n        trunk_id,\n        updated_at\n    from fields\n)\n\nselect *\nfrom final", "relation_name": "`dbt-package-testing`.`twilio_source_integration_tests_1_twilio_source`.`stg_twilio__call`"}, {"status": "success", "timing": [{"name": "compile", "started_at": "2024-07-02T20:46:48.414231Z", "completed_at": "2024-07-02T20:46:49.260894Z"}, {"name": "execute", "started_at": "2024-07-02T20:46:49.267667Z", "completed_at": "2024-07-02T20:46:49.267670Z"}], "thread_id": "Thread-2 (worker)", "execution_time": 0.8556020259857178, "adapter_response": {}, "message": null, "failures": null, "unique_id": "model.twilio_source.stg_twilio__incoming_phone_number", "compiled": true, "compiled_code": "with base as (\n\n    select * \n    from `dbt-package-testing`.`twilio_source_integration_tests_1_twilio_source`.`stg_twilio__incoming_phone_number_tmp`\n),\n\nfields as (\n\n    select\n        \n    \n    \n    _fivetran_synced\n    \n as \n    \n    _fivetran_synced\n    \n, \n    \n    \n    account_id\n    \n as \n    \n    account_id\n    \n, \n    \n    \n    address_id\n    \n as \n    \n    address_id\n    \n, \n    \n    \n    address_requirements\n    \n as \n    \n    address_requirements\n    \n, \n    \n    \n    beta\n    \n as \n    \n    beta\n    \n, \n    \n    \n    capabilities_mms\n    \n as \n    \n    capabilities_mms\n    \n, \n    \n    \n    capabilities_sms\n    \n as \n    \n    capabilities_sms\n    \n, \n    \n    \n    capabilities_voice\n    \n as \n    \n    capabilities_voice\n    \n, \n    \n    \n    created_at\n    \n as \n    \n    created_at\n    \n, \n    \n    \n    emergency_address_id\n    \n as \n    \n    emergency_address_id\n    \n, \n    \n    \n    emergency_status\n    \n as \n    \n    emergency_status\n    \n, \n    \n    \n    friendly_name\n    \n as \n    \n    friendly_name\n    \n, \n    \n    \n    id\n    \n as \n    \n    id\n    \n, \n    \n    \n    origin\n    \n as \n    \n    origin\n    \n, \n    \n    \n    phone_number\n    \n as \n    \n    phone_number\n    \n, \n    \n    \n    trunk_id\n    \n as \n    \n    trunk_id\n    \n, \n    \n    \n    updated_at\n    \n as \n    \n    updated_at\n    \n, \n    \n    \n    voice_caller_id_lookup\n    \n as \n    \n    voice_caller_id_lookup\n    \n, \n    \n    \n    voice_url\n    \n as \n    \n    voice_url\n    \n\n\n\n    from base\n),\n\nfinal as (\n    \n    select \n        _fivetran_synced,\n        account_id,\n        cast(address_id as string) as address_id, \n        capabilities_mms,\n        capabilities_sms,\n        capabilities_voice,\n        created_at,\n        emergency_address_id,\n        emergency_status,\n        friendly_name,\n        id as incoming_phone_number_id,\n        origin,\n        phone_number,\n        trunk_id,\n        updated_at,\n        voice_caller_id_lookup,\n        voice_url\n    from fields\n)\n\nselect *\nfrom final", "relation_name": "`dbt-package-testing`.`twilio_source_integration_tests_1_twilio_source`.`stg_twilio__incoming_phone_number`"}, {"status": "success", "timing": [{"name": "compile", "started_at": "2024-07-02T20:46:48.420109Z", "completed_at": "2024-07-02T20:46:49.261102Z"}, {"name": "execute", "started_at": "2024-07-02T20:46:49.267871Z", "completed_at": "2024-07-02T20:46:49.267874Z"}], "thread_id": "Thread-1 (worker)", "execution_time": 0.8495359420776367, "adapter_response": {}, "message": null, "failures": null, "unique_id": "model.twilio_source.stg_twilio__account_history", "compiled": true, "compiled_code": "with base as (\n\n    select * \n    from `dbt-package-testing`.`twilio_source_integration_tests_1_twilio_source`.`stg_twilio__account_history_tmp`\n),\n\nfields as (\n\n    select\n        \n    \n    \n    _fivetran_synced\n    \n as \n    \n    _fivetran_synced\n    \n, \n    \n    \n    created_at\n    \n as \n    \n    created_at\n    \n, \n    \n    \n    friendly_name\n    \n as \n    \n    friendly_name\n    \n, \n    \n    \n    id\n    \n as \n    \n    id\n    \n, \n    \n    \n    owner_account_id\n    \n as \n    \n    owner_account_id\n    \n, \n    \n    \n    status\n    \n as \n    \n    status\n    \n, \n    \n    \n    type\n    \n as \n    \n    type\n    \n, \n    \n    \n    updated_at\n    \n as \n    \n    updated_at\n    \n\n\n\n    from base\n),\n\nfinal as (\n    \n    select \n        _fivetran_synced,\n        created_at,\n        friendly_name,\n        id as account_id,\n        owner_account_id,\n        status,\n        type,\n        updated_at,\n        row_number() over (partition by id order by updated_at desc) = 1 as is_most_recent_record\n    from fields\n)\n\nselect *\nfrom final", "relation_name": "`dbt-package-testing`.`twilio_source_integration_tests_1_twilio_source`.`stg_twilio__account_history`"}, {"status": "success", "timing": [{"name": "compile", "started_at": "2024-07-02T20:46:48.416641Z", "completed_at": "2024-07-02T20:46:49.268683Z"}, {"name": "execute", "started_at": "2024-07-02T20:46:49.270510Z", "completed_at": "2024-07-02T20:46:49.270513Z"}], "thread_id": "Thread-4 (worker)", "execution_time": 0.8601710796356201, "adapter_response": {}, "message": null, "failures": null, "unique_id": "model.twilio_source.stg_twilio__address", "compiled": true, "compiled_code": "with base as (\n\n    select * \n    from `dbt-package-testing`.`twilio_source_integration_tests_1_twilio_source`.`stg_twilio__address_tmp`\n),\n\nfields as (\n\n    select\n        \n    \n    \n    _fivetran_synced\n    \n as \n    \n    _fivetran_synced\n    \n, \n    \n    \n    account_id\n    \n as \n    \n    account_id\n    \n, \n    \n    \n    city\n    \n as \n    \n    city\n    \n, \n    \n    \n    created_at\n    \n as \n    \n    created_at\n    \n, \n    \n    \n    customer_name\n    \n as \n    \n    customer_name\n    \n, \n    \n    \n    emergency_enabled\n    \n as \n    \n    emergency_enabled\n    \n, \n    \n    \n    friendly_name\n    \n as \n    \n    friendly_name\n    \n, \n    \n    \n    id\n    \n as \n    \n    id\n    \n, \n    \n    \n    iso_country\n    \n as \n    \n    iso_country\n    \n, \n    \n    \n    postal_code\n    \n as \n    \n    postal_code\n    \n, \n    \n    \n    region\n    \n as \n    \n    region\n    \n, \n    \n    \n    street\n    \n as \n    \n    street\n    \n, \n    \n    \n    updated_at\n    \n as \n    \n    updated_at\n    \n, \n    \n    \n    validated\n    \n as \n    \n    validated\n    \n, \n    \n    \n    verified\n    \n as \n    \n    verified\n    \n\n\n\n    from base\n),\n\nfinal as (\n    \n    select \n        _fivetran_synced,\n        account_id,\n        city,\n        created_at,\n        customer_name,\n        emergency_enabled,\n        friendly_name,\n        cast(id as string) as address_id,\n        iso_country,\n        postal_code,\n        region,\n        street,\n        updated_at,\n        validated,\n        verified\n    from fields\n)\n\nselect *\nfrom final", "relation_name": "`dbt-package-testing`.`twilio_source_integration_tests_1_twilio_source`.`stg_twilio__address`"}, {"status": "success", "timing": [{"name": "compile", "started_at": "2024-07-02T20:46:49.278906Z", "completed_at": "2024-07-02T20:46:50.042280Z"}, {"name": "execute", "started_at": "2024-07-02T20:46:50.043592Z", "completed_at": "2024-07-02T20:46:50.043597Z"}], "thread_id": "Thread-4 (worker)", "execution_time": 0.7665698528289795, "adapter_response": {}, "message": null, "failures": null, "unique_id": "model.twilio_source.stg_twilio__usage_record", "compiled": true, "compiled_code": "with base as (\n\n    select * \n    from `dbt-package-testing`.`twilio_source_integration_tests_1_twilio_source`.`stg_twilio__usage_record_tmp`\n),\n\nfields as (\n\n    select\n        \n    \n    \n    _fivetran_synced\n    \n as \n    \n    _fivetran_synced\n    \n, \n    \n    \n    account_id\n    \n as \n    \n    account_id\n    \n, \n    \n    \n    as_of\n    \n as \n    \n    as_of\n    \n, \n    \n    \n    category\n    \n as \n    \n    category\n    \n, \n    \n    \n    count\n    \n as \n    \n    count\n    \n, \n    \n    \n    count_unit\n    \n as \n    \n    count_unit\n    \n, \n    \n    \n    description\n    \n as \n    \n    description\n    \n, \n    \n    \n    end_date\n    \n as \n    \n    end_date\n    \n, \n    \n    \n    price\n    \n as \n    \n    price\n    \n, \n    \n    \n    price_unit\n    \n as \n    \n    price_unit\n    \n, \n    \n    \n    start_date\n    \n as \n    \n    start_date\n    \n, \n    \n    \n    usage\n    \n as \n    \n    usage\n    \n, \n    \n    \n    usage_unit\n    \n as \n    \n    usage_unit\n    \n\n\n\n    from base\n),\n\nfinal as (\n    \n    select \n        _fivetran_synced,\n        account_id,\n        as_of,\n        category,\n        cast(count as FLOAT64) as count,\n        count_unit,\n        description,\n        end_date,\n        cast(price as FLOAT64) as price,\n        price_unit,\n        start_date,\n        cast(usage as FLOAT64) as usage,\n        usage_unit\n    from fields\n)\n\nselect *\nfrom final", "relation_name": "`dbt-package-testing`.`twilio_source_integration_tests_1_twilio_source`.`stg_twilio__usage_record`"}, {"status": "success", "timing": [{"name": "compile", "started_at": "2024-07-02T20:46:49.270980Z", "completed_at": "2024-07-02T20:46:50.042534Z"}, {"name": "execute", "started_at": "2024-07-02T20:46:50.043824Z", "completed_at": "2024-07-02T20:46:50.043827Z"}], "thread_id": "Thread-3 (worker)", "execution_time": 0.775688886642456, "adapter_response": {}, "message": null, "failures": null, "unique_id": "model.twilio_source.stg_twilio__message", "compiled": true, "compiled_code": "with base as (\n\n    select * \n    from `dbt-package-testing`.`twilio_source_integration_tests_1_twilio_source`.`stg_twilio__message_tmp`\n),\n\nfields as (\n\n    select\n        \n    \n    \n    _fivetran_synced\n    \n as \n    \n    _fivetran_synced\n    \n, \n    \n    \n    account_id\n    \n as \n    \n    account_id\n    \n, \n    \n    \n    body\n    \n as \n    \n    body\n    \n, \n    \n    \n    created_at\n    \n as \n    \n    created_at\n    \n, \n    \n    \n    date_sent\n    \n as \n    \n    date_sent\n    \n, \n    \n    \n    direction\n    \n as \n    \n    direction\n    \n, \n    \n    \n    error_code\n    \n as \n    \n    error_code\n    \n, \n    \n    \n    error_message\n    \n as \n    \n    error_message\n    \n, \n    \n    \n    id\n    \n as \n    \n    id\n    \n, \n    \n    \n    messaging_service_sid\n    \n as \n    \n    messaging_service_sid\n    \n, \n    \n    \n    num_media\n    \n as \n    \n    num_media\n    \n, \n    \n    \n    num_segments\n    \n as \n    \n    num_segments\n    \n, \n    \n    \n    price\n    \n as \n    \n    price\n    \n, \n    \n    \n    price_unit\n    \n as \n    \n    price_unit\n    \n, \n    \n    \n    status\n    \n as \n    \n    status\n    \n, \n    \n    \n    updated_at\n    \n as \n    \n    updated_at\n    \n, \n    \n    \n        \n            \n            `from`\n            \n        \n    \n as message_from , \n    \n    \n        \n            \n            `to`\n            \n        \n    \n as message_to \n\n\n    from base\n),\n\nfinal as (\n    \n    select \n        _fivetran_synced,\n        account_id,\n        body,\n        created_at,\n        cast(date_sent as timestamp) as timestamp_sent,\n        direction,\n        error_code,\n        error_message,\n        message_from, -- renamed in the get_message_columns macro\n        id as message_id,\n        cast(messaging_service_sid as string) as messaging_service_id,\n        cast(num_media as FLOAT64) as num_media,\n        cast(num_segments as FLOAT64) as num_segments,\n        cast(price as FLOAT64) as price,\n        price_unit,\n        status,\n        message_to, -- renamed in the get_message_columns macro\n        updated_at\n    from fields\n)\n\nselect *\nfrom final", "relation_name": "`dbt-package-testing`.`twilio_source_integration_tests_1_twilio_source`.`stg_twilio__message`"}, {"status": "success", "timing": [{"name": "compile", "started_at": "2024-07-02T20:46:49.274178Z", "completed_at": "2024-07-02T20:46:50.042791Z"}, {"name": "execute", "started_at": "2024-07-02T20:46:50.044047Z", "completed_at": "2024-07-02T20:46:50.044050Z"}], "thread_id": "Thread-2 (worker)", "execution_time": 0.775068998336792, "adapter_response": {}, "message": null, "failures": null, "unique_id": "model.twilio_source.stg_twilio__messaging_service", "compiled": true, "compiled_code": "--To disable this model, set the using_twilio_messaging_service variable within your dbt_project.yml file to False.\n\n\nwith base as (\n\n    select * \n    from `dbt-package-testing`.`twilio_source_integration_tests_1_twilio_source`.`stg_twilio__messaging_service_tmp`\n),\n\nfields as (\n\n    select\n        \n    \n    \n    _fivetran_deleted\n    \n as \n    \n    _fivetran_deleted\n    \n, \n    \n    \n    _fivetran_synced\n    \n as \n    \n    _fivetran_synced\n    \n, \n    \n    \n    account_id\n    \n as \n    \n    account_id\n    \n, \n    \n    \n    area_code_geomatch\n    \n as \n    \n    area_code_geomatch\n    \n, \n    \n    \n    created_at\n    \n as \n    \n    created_at\n    \n, \n    \n    \n    fallback_method\n    \n as \n    \n    fallback_method\n    \n, \n    \n    \n    fallback_to_long_code\n    \n as \n    \n    fallback_to_long_code\n    \n, \n    \n    \n    fallback_url\n    \n as \n    \n    fallback_url\n    \n, \n    \n    \n    friendly_name\n    \n as \n    \n    friendly_name\n    \n, \n    \n    \n    id\n    \n as \n    \n    id\n    \n, \n    \n    \n    inbound_method\n    \n as \n    \n    inbound_method\n    \n, \n    \n    \n    inbound_request_url\n    \n as \n    \n    inbound_request_url\n    \n, \n    \n    \n    mms_converter\n    \n as \n    \n    mms_converter\n    \n, \n    \n    \n    scan_message_content\n    \n as \n    \n    scan_message_content\n    \n, \n    \n    \n    smart_encoding\n    \n as \n    \n    smart_encoding\n    \n, \n    \n    \n    status_callback\n    \n as \n    \n    status_callback\n    \n, \n    \n    \n    sticky_sender\n    \n as \n    \n    sticky_sender\n    \n, \n    \n    \n    synchronous_validation\n    \n as \n    \n    synchronous_validation\n    \n, \n    \n    \n    updated_at\n    \n as \n    \n    updated_at\n    \n, \n    \n    \n    us_app_to_person_registered\n    \n as \n    \n    us_app_to_person_registered\n    \n, \n    \n    \n    use_inbound_webhook_on_number\n    \n as \n    \n    use_inbound_webhook_on_number\n    \n, \n    \n    \n    usecase\n    \n as \n    \n    usecase\n    \n, \n    \n    \n    validity_period\n    \n as \n    \n    validity_period\n    \n\n\n\n    from base\n),\n\nfinal as (\n    \n    select \n        _fivetran_deleted,\n        _fivetran_synced,\n        account_id,\n        area_code_geomatch,\n        created_at,\n        fallback_method,\n        fallback_to_long_code,\n        fallback_url,\n        friendly_name,\n        cast(id as string) as messaging_service_id,\n        inbound_method,\n        inbound_request_url,\n        mms_converter,\n        scan_message_content,\n        smart_encoding,\n        status_callback,\n        sticky_sender,\n        synchronous_validation,\n        updated_at,\n        us_app_to_person_registered,\n        use_inbound_webhook_on_number,\n        usecase as use_case,\n        validity_period\n    from fields\n)\n\nselect *\nfrom final", "relation_name": "`dbt-package-testing`.`twilio_source_integration_tests_1_twilio_source`.`stg_twilio__messaging_service`"}, {"status": "success", "timing": [{"name": "compile", "started_at": "2024-07-02T20:46:50.057140Z", "completed_at": "2024-07-02T20:46:50.059479Z"}, {"name": "execute", "started_at": "2024-07-02T20:46:50.060559Z", "completed_at": "2024-07-02T20:46:50.060563Z"}], "thread_id": "Thread-2 (worker)", "execution_time": 0.014108896255493164, "adapter_response": {}, "message": null, "failures": null, "unique_id": "test.twilio_source.not_null_stg_twilio__incoming_phone_number_incoming_phone_number_id.9a63d01724", "compiled": true, "compiled_code": "\n    \n    \n\n\n\nselect incoming_phone_number_id\nfrom `dbt-package-testing`.`twilio_source_integration_tests_1_twilio_source`.`stg_twilio__incoming_phone_number`\nwhere incoming_phone_number_id is null\n\n\n", "relation_name": null}, {"status": "success", "timing": [{"name": "compile", "started_at": "2024-07-02T20:46:50.054265Z", "completed_at": "2024-07-02T20:46:50.059698Z"}, {"name": "execute", "started_at": "2024-07-02T20:46:50.060752Z", "completed_at": "2024-07-02T20:46:50.060755Z"}], "thread_id": "Thread-3 (worker)", "execution_time": 0.014864206314086914, "adapter_response": {}, "message": null, "failures": null, "unique_id": "test.twilio_source.unique_stg_twilio__call_call_id.4a911440b6", "compiled": true, "compiled_code": "\n    \n    \n\nwith dbt_test__target as (\n\n  select call_id as unique_field\n  from `dbt-package-testing`.`twilio_source_integration_tests_1_twilio_source`.`stg_twilio__call`\n  where call_id is not null\n\n)\n\nselect\n    unique_field,\n    count(*) as n_records\n\nfrom dbt_test__target\ngroup by unique_field\nhaving count(*) > 1\n\n\n", "relation_name": null}, {"status": "success", "timing": [{"name": "compile", "started_at": "2024-07-02T20:46:50.048085Z", "completed_at": "2024-07-02T20:46:50.059895Z"}, {"name": "execute", "started_at": "2024-07-02T20:46:50.060934Z", "completed_at": "2024-07-02T20:46:50.060936Z"}], "thread_id": "Thread-4 (worker)", "execution_time": 0.015550851821899414, "adapter_response": {}, "message": null, "failures": null, "unique_id": "test.twilio_source.not_null_stg_twilio__call_call_id.b1c7afdc81", "compiled": true, "compiled_code": "\n    \n    \n\n\n\nselect call_id\nfrom `dbt-package-testing`.`twilio_source_integration_tests_1_twilio_source`.`stg_twilio__call`\nwhere call_id is null\n\n\n", "relation_name": null}, {"status": "success", "timing": [{"name": "compile", "started_at": "2024-07-02T20:46:50.064189Z", "completed_at": "2024-07-02T20:46:50.072355Z"}, {"name": "execute", "started_at": "2024-07-02T20:46:50.072711Z", "completed_at": "2024-07-02T20:46:50.072715Z"}], "thread_id": "Thread-2 (worker)", "execution_time": 0.010371208190917969, "adapter_response": {}, "message": null, "failures": null, "unique_id": "test.twilio_source.unique_stg_twilio__incoming_phone_number_incoming_phone_number_id.d6eb15efc6", "compiled": true, "compiled_code": "\n    \n    \n\nwith dbt_test__target as (\n\n  select incoming_phone_number_id as unique_field\n  from `dbt-package-testing`.`twilio_source_integration_tests_1_twilio_source`.`stg_twilio__incoming_phone_number`\n  where incoming_phone_number_id is not null\n\n)\n\nselect\n    unique_field,\n    count(*) as n_records\n\nfrom dbt_test__target\ngroup by unique_field\nhaving count(*) > 1\n\n\n", "relation_name": null}, {"status": "success", "timing": [{"name": "compile", "started_at": "2024-07-02T20:46:50.066122Z", "completed_at": "2024-07-02T20:46:50.072885Z"}, {"name": "execute", "started_at": "2024-07-02T20:46:50.074053Z", "completed_at": "2024-07-02T20:46:50.074056Z"}], "thread_id": "Thread-3 (worker)", "execution_time": 0.011665105819702148, "adapter_response": {}, "message": null, "failures": null, "unique_id": "test.twilio_source.dbt_utils_unique_combination_of_columns_stg_twilio__account_history_account_id__updated_at.0bcbfc5896", "compiled": true, "compiled_code": "\n\n\n\n\n\nwith validation_errors as (\n\n    select\n        account_id, updated_at\n    from `dbt-package-testing`.`twilio_source_integration_tests_1_twilio_source`.`stg_twilio__account_history`\n    group by account_id, updated_at\n    having count(*) > 1\n\n)\n\nselect *\nfrom validation_errors\n\n\n", "relation_name": null}, {"status": "success", "timing": [{"name": "compile", "started_at": "2024-07-02T20:46:50.070360Z", "completed_at": "2024-07-02T20:46:50.073393Z"}, {"name": "execute", "started_at": "2024-07-02T20:46:50.074489Z", "completed_at": "2024-07-02T20:46:50.074491Z"}], "thread_id": "Thread-4 (worker)", "execution_time": 0.01186990737915039, "adapter_response": {}, "message": null, "failures": null, "unique_id": "test.twilio_source.not_null_stg_twilio__account_history_account_id.9d783e8ba5", "compiled": true, "compiled_code": "\n    \n    \n\n\n\nselect account_id\nfrom `dbt-package-testing`.`twilio_source_integration_tests_1_twilio_source`.`stg_twilio__account_history`\nwhere account_id is null\n\n\n", "relation_name": null}, {"status": "success", "timing": [{"name": "compile", "started_at": "2024-07-02T20:46:50.075661Z", "completed_at": "2024-07-02T20:46:50.079417Z"}, {"name": "execute", "started_at": "2024-07-02T20:46:50.082934Z", "completed_at": "2024-07-02T20:46:50.082937Z"}], "thread_id": "Thread-2 (worker)", "execution_time": 0.009041070938110352, "adapter_response": {}, "message": null, "failures": null, "unique_id": "test.twilio_source.not_null_stg_twilio__account_history_updated_at.d6e6f7f215", "compiled": true, "compiled_code": "\n    \n    \n\n\n\nselect updated_at\nfrom `dbt-package-testing`.`twilio_source_integration_tests_1_twilio_source`.`stg_twilio__account_history`\nwhere updated_at is null\n\n\n", "relation_name": null}, {"status": "success", "timing": [{"name": "compile", "started_at": "2024-07-02T20:46:50.081199Z", "completed_at": "2024-07-02T20:46:50.083503Z"}, {"name": "execute", "started_at": "2024-07-02T20:46:50.084628Z", "completed_at": "2024-07-02T20:46:50.084631Z"}], "thread_id": "Thread-4 (worker)", "execution_time": 0.006536006927490234, "adapter_response": {}, "message": null, "failures": null, "unique_id": "test.twilio_source.unique_stg_twilio__address_address_id.4629d76478", "compiled": true, "compiled_code": "\n    \n    \n\nwith dbt_test__target as (\n\n  select address_id as unique_field\n  from `dbt-package-testing`.`twilio_source_integration_tests_1_twilio_source`.`stg_twilio__address`\n  where address_id is not null\n\n)\n\nselect\n    unique_field,\n    count(*) as n_records\n\nfrom dbt_test__target\ngroup by unique_field\nhaving count(*) > 1\n\n\n", "relation_name": null}, {"status": "success", "timing": [{"name": "compile", "started_at": "2024-07-02T20:46:50.079586Z", "completed_at": "2024-07-02T20:46:50.083830Z"}, {"name": "execute", "started_at": "2024-07-02T20:46:50.085014Z", "completed_at": "2024-07-02T20:46:50.085017Z"}], "thread_id": "Thread-3 (worker)", "execution_time": 0.009598016738891602, "adapter_response": {}, "message": null, "failures": null, "unique_id": "test.twilio_source.not_null_stg_twilio__address_address_id.88b6a635a6", "compiled": true, "compiled_code": "\n    \n    \n\n\n\nselect address_id\nfrom `dbt-package-testing`.`twilio_source_integration_tests_1_twilio_source`.`stg_twilio__address`\nwhere address_id is null\n\n\n", "relation_name": null}, {"status": "success", "timing": [{"name": "compile", "started_at": "2024-07-02T20:46:50.085593Z", "completed_at": "2024-07-02T20:46:50.089266Z"}, {"name": "execute", "started_at": "2024-07-02T20:46:50.093207Z", "completed_at": "2024-07-02T20:46:50.093211Z"}], "thread_id": "Thread-2 (worker)", "execution_time": 0.009367942810058594, "adapter_response": {}, "message": null, "failures": null, "unique_id": "test.twilio_source.dbt_utils_unique_combination_of_columns_stg_twilio__usage_record_category__start_date__end_date__account_id.3782e14f70", "compiled": true, "compiled_code": "\n\n\n\n\n\nwith validation_errors as (\n\n    select\n        category, start_date, end_date, account_id\n    from `dbt-package-testing`.`twilio_source_integration_tests_1_twilio_source`.`stg_twilio__usage_record`\n    group by category, start_date, end_date, account_id\n    having count(*) > 1\n\n)\n\nselect *\nfrom validation_errors\n\n\n", "relation_name": null}, {"status": "success", "timing": [{"name": "compile", "started_at": "2024-07-02T20:46:50.091572Z", "completed_at": "2024-07-02T20:46:50.094024Z"}, {"name": "execute", "started_at": "2024-07-02T20:46:50.095034Z", "completed_at": "2024-07-02T20:46:50.095037Z"}], "thread_id": "Thread-3 (worker)", "execution_time": 0.00821828842163086, "adapter_response": {}, "message": null, "failures": null, "unique_id": "test.twilio_source.not_null_stg_twilio__usage_record_category.e6d57544df", "compiled": true, "compiled_code": "\n    \n    \n\n\n\nselect category\nfrom `dbt-package-testing`.`twilio_source_integration_tests_1_twilio_source`.`stg_twilio__usage_record`\nwhere category is null\n\n\n", "relation_name": null}, {"status": "success", "timing": [{"name": "compile", "started_at": "2024-07-02T20:46:50.089923Z", "completed_at": "2024-07-02T20:46:50.094426Z"}, {"name": "execute", "started_at": "2024-07-02T20:46:50.096929Z", "completed_at": "2024-07-02T20:46:50.096932Z"}], "thread_id": "Thread-4 (worker)", "execution_time": 0.008840084075927734, "adapter_response": {}, "message": null, "failures": null, "unique_id": "test.twilio_source.not_null_stg_twilio__usage_record_account_id.8b387072fd", "compiled": true, "compiled_code": "\n    \n    \n\n\n\nselect account_id\nfrom `dbt-package-testing`.`twilio_source_integration_tests_1_twilio_source`.`stg_twilio__usage_record`\nwhere account_id is null\n\n\n", "relation_name": null}, {"status": "success", "timing": [{"name": "compile", "started_at": "2024-07-02T20:46:50.095216Z", "completed_at": "2024-07-02T20:46:50.097978Z"}, {"name": "execute", "started_at": "2024-07-02T20:46:50.099120Z", "completed_at": "2024-07-02T20:46:50.099123Z"}], "thread_id": "Thread-2 (worker)", "execution_time": 0.0069501399993896484, "adapter_response": {}, "message": null, "failures": null, "unique_id": "test.twilio_source.not_null_stg_twilio__usage_record_end_date.0f8fc2406e", "compiled": true, "compiled_code": "\n    \n    \n\n\n\nselect end_date\nfrom `dbt-package-testing`.`twilio_source_integration_tests_1_twilio_source`.`stg_twilio__usage_record`\nwhere end_date is null\n\n\n", "relation_name": null}, {"status": "success", "timing": [{"name": "compile", "started_at": "2024-07-02T20:46:50.099419Z", "completed_at": "2024-07-02T20:46:50.103751Z"}, {"name": "execute", "started_at": "2024-07-02T20:46:50.106861Z", "completed_at": "2024-07-02T20:46:50.106865Z"}], "thread_id": "Thread-3 (worker)", "execution_time": 0.009047985076904297, "adapter_response": {}, "message": null, "failures": null, "unique_id": "test.twilio_source.not_null_stg_twilio__usage_record_start_date.a73353be1b", "compiled": true, "compiled_code": "\n    \n    \n\n\n\nselect start_date\nfrom `dbt-package-testing`.`twilio_source_integration_tests_1_twilio_source`.`stg_twilio__usage_record`\nwhere start_date is null\n\n\n", "relation_name": null}, {"status": "success", "timing": [{"name": "compile", "started_at": "2024-07-02T20:46:50.101324Z", "completed_at": "2024-07-02T20:46:50.104065Z"}, {"name": "execute", "started_at": "2024-07-02T20:46:50.107059Z", "completed_at": "2024-07-02T20:46:50.107062Z"}], "thread_id": "Thread-4 (worker)", "execution_time": 0.009137153625488281, "adapter_response": {}, "message": null, "failures": null, "unique_id": "test.twilio_source.dbt_utils_unique_combination_of_columns_stg_twilio__message_account_id__message_id__messaging_service_id.2696e90a8e", "compiled": true, "compiled_code": "\n\n\n\n\n\nwith validation_errors as (\n\n    select\n        account_id, message_id, messaging_service_id\n    from `dbt-package-testing`.`twilio_source_integration_tests_1_twilio_source`.`stg_twilio__message`\n    group by account_id, message_id, messaging_service_id\n    having count(*) > 1\n\n)\n\nselect *\nfrom validation_errors\n\n\n", "relation_name": null}, {"status": "success", "timing": [{"name": "compile", "started_at": "2024-07-02T20:46:50.104390Z", "completed_at": "2024-07-02T20:46:50.107588Z"}, {"name": "execute", "started_at": "2024-07-02T20:46:50.108815Z", "completed_at": "2024-07-02T20:46:50.108817Z"}], "thread_id": "Thread-2 (worker)", "execution_time": 0.0060100555419921875, "adapter_response": {}, "message": null, "failures": null, "unique_id": "test.twilio_source.not_null_stg_twilio__message_account_id.4e63c023d2", "compiled": true, "compiled_code": "\n    \n    \n\n\n\nselect account_id\nfrom `dbt-package-testing`.`twilio_source_integration_tests_1_twilio_source`.`stg_twilio__message`\nwhere account_id is null\n\n\n", "relation_name": null}, {"status": "success", "timing": [{"name": "compile", "started_at": "2024-07-02T20:46:50.109866Z", "completed_at": "2024-07-02T20:46:50.113700Z"}, {"name": "execute", "started_at": "2024-07-02T20:46:50.115978Z", "completed_at": "2024-07-02T20:46:50.115981Z"}], "thread_id": "Thread-3 (worker)", "execution_time": 0.008063077926635742, "adapter_response": {}, "message": null, "failures": null, "unique_id": "test.twilio_source.not_null_stg_twilio__message_message_id.bc1b8551d4", "compiled": true, "compiled_code": "\n    \n    \n\n\n\nselect message_id\nfrom `dbt-package-testing`.`twilio_source_integration_tests_1_twilio_source`.`stg_twilio__message`\nwhere message_id is null\n\n\n", "relation_name": null}, {"status": "success", "timing": [{"name": "compile", "started_at": "2024-07-02T20:46:50.111664Z", "completed_at": "2024-07-02T20:46:50.115439Z"}, {"name": "execute", "started_at": "2024-07-02T20:46:50.116331Z", "completed_at": "2024-07-02T20:46:50.116334Z"}], "thread_id": "Thread-4 (worker)", "execution_time": 0.008125782012939453, "adapter_response": {}, "message": null, "failures": null, "unique_id": "test.twilio_source.dbt_utils_unique_combination_of_columns_stg_twilio__messaging_service_account_id__messaging_service_id.2de8528f3d", "compiled": true, "compiled_code": "\n\n\n\n\n\nwith validation_errors as (\n\n    select\n        account_id, messaging_service_id\n    from `dbt-package-testing`.`twilio_source_integration_tests_1_twilio_source`.`stg_twilio__messaging_service`\n    group by account_id, messaging_service_id\n    having count(*) > 1\n\n)\n\nselect *\nfrom validation_errors\n\n\n", "relation_name": null}, {"status": "success", "timing": [{"name": "compile", "started_at": "2024-07-02T20:46:50.113874Z", "completed_at": "2024-07-02T20:46:50.116154Z"}, {"name": "execute", "started_at": "2024-07-02T20:46:50.117472Z", "completed_at": "2024-07-02T20:46:50.117474Z"}], "thread_id": "Thread-2 (worker)", "execution_time": 0.004854917526245117, "adapter_response": {}, "message": null, "failures": null, "unique_id": "test.twilio_source.not_null_stg_twilio__messaging_service_account_id.f46a18a677", "compiled": true, "compiled_code": "\n    \n    \n\n\n\nselect account_id\nfrom `dbt-package-testing`.`twilio_source_integration_tests_1_twilio_source`.`stg_twilio__messaging_service`\nwhere account_id is null\n\n\n", "relation_name": null}, {"status": "success", "timing": [{"name": "compile", "started_at": "2024-07-02T20:46:50.118479Z", "completed_at": "2024-07-02T20:46:50.120212Z"}, {"name": "execute", "started_at": "2024-07-02T20:46:50.120530Z", "completed_at": "2024-07-02T20:46:50.120532Z"}], "thread_id": "Thread-3 (worker)", "execution_time": 0.0030989646911621094, "adapter_response": {}, "message": null, "failures": null, "unique_id": "test.twilio_source.not_null_stg_twilio__messaging_service_messaging_service_id.c7032fe946", "compiled": true, "compiled_code": "\n    \n    \n\n\n\nselect messaging_service_id\nfrom `dbt-package-testing`.`twilio_source_integration_tests_1_twilio_source`.`stg_twilio__messaging_service`\nwhere messaging_service_id is null\n\n\n", "relation_name": null}, {"status": "success", "timing": [{"name": "compile", "started_at": "2024-07-02T20:46:49.276286Z", "completed_at": "2024-07-02T20:46:50.183713Z"}, {"name": "execute", "started_at": "2024-07-02T20:46:50.184111Z", "completed_at": "2024-07-02T20:46:50.184115Z"}], "thread_id": "Thread-1 (worker)", "execution_time": 0.9137868881225586, "adapter_response": {}, "message": null, "failures": null, "unique_id": "model.twilio_source.stg_twilio__outgoing_caller_id", "compiled": true, "compiled_code": "with base as (\n\n    select * \n    from `dbt-package-testing`.`twilio_source_integration_tests_1_twilio_source`.`stg_twilio__outgoing_caller_id_tmp`\n),\n\nfields as (\n\n    select\n        \n    \n    \n    _fivetran_synced\n    \n as \n    \n    _fivetran_synced\n    \n, \n    \n    \n    created_at\n    \n as \n    \n    created_at\n    \n, \n    \n    \n    friendly_name\n    \n as \n    \n    friendly_name\n    \n, \n    \n    \n    id\n    \n as \n    \n    id\n    \n, \n    \n    \n    phone_number\n    \n as \n    \n    phone_number\n    \n, \n    \n    \n    updated_at\n    \n as \n    \n    updated_at\n    \n\n\n\n    from base\n),\n\nfinal as (\n    \n    select \n        _fivetran_synced,\n        created_at,\n        friendly_name,\n        id as outgoing_caller_id,\n        phone_number,\n        updated_at\n    from fields\n)\n\nselect *\nfrom final", "relation_name": "`dbt-package-testing`.`twilio_source_integration_tests_1_twilio_source`.`stg_twilio__outgoing_caller_id`"}, {"status": "success", "timing": [{"name": "compile", "started_at": "2024-07-02T20:46:50.186270Z", "completed_at": "2024-07-02T20:46:50.190290Z"}, {"name": "execute", "started_at": "2024-07-02T20:46:50.190685Z", "completed_at": "2024-07-02T20:46:50.190688Z"}], "thread_id": "Thread-4 (worker)", "execution_time": 0.005986690521240234, "adapter_response": {}, "message": null, "failures": null, "unique_id": "test.twilio_source.not_null_stg_twilio__outgoing_caller_id_outgoing_caller_id.de6e667878", "compiled": true, "compiled_code": "\n    \n    \n\n\n\nselect outgoing_caller_id\nfrom `dbt-package-testing`.`twilio_source_integration_tests_1_twilio_source`.`stg_twilio__outgoing_caller_id`\nwhere outgoing_caller_id is null\n\n\n", "relation_name": null}, {"status": "success", "timing": [{"name": "compile", "started_at": "2024-07-02T20:46:50.188313Z", "completed_at": "2024-07-02T20:46:50.190873Z"}, {"name": "execute", "started_at": "2024-07-02T20:46:50.191763Z", "completed_at": "2024-07-02T20:46:50.191767Z"}], "thread_id": "Thread-2 (worker)", "execution_time": 0.006480693817138672, "adapter_response": {}, "message": null, "failures": null, "unique_id": "test.twilio_source.unique_stg_twilio__outgoing_caller_id_outgoing_caller_id.0e55c1c2ea", "compiled": true, "compiled_code": "\n    \n    \n\nwith dbt_test__target as (\n\n  select outgoing_caller_id as unique_field\n  from `dbt-package-testing`.`twilio_source_integration_tests_1_twilio_source`.`stg_twilio__outgoing_caller_id`\n  where outgoing_caller_id is not null\n\n)\n\nselect\n    unique_field,\n    count(*) as n_records\n\nfrom dbt_test__target\ngroup by unique_field\nhaving count(*) > 1\n\n\n", "relation_name": null}], "elapsed_time": 5.172059059143066, "args": {"introspect": true, "favor_state": false, "send_anonymous_usage_stats": true, "use_colors": true, "compile": true, "which": "generate", "empty_catalog": false, "vars": {}, "enable_legacy_logger": false, "quiet": false, "select": [], "print": true, "write_json": true, "project_dir": "/Users/renee/Documents/dbt/twilio/dbt_twilio_source/integration_tests", "macro_debugging": false, "profiles_dir": "/Users/renee/.dbt", "log_format_file": "debug", "log_path": "/Users/renee/Documents/dbt/twilio/dbt_twilio_source/integration_tests/logs", "static": false, "static_parser": true, "log_file_max_bytes": 10485760, "populate_cache": true, "printer_width": 80, "defer": false, "use_colors_file": true, "version_check": true, "indirect_selection": "eager", "log_format": "default", "log_level": "info", "strict_mode": false, "exclude": [], "log_level_file": "debug", "partial_parse": true, "invocation_command": "dbt docs generate", "partial_parse_file_diff": true, "show_resource_report": false, "warn_error_options": {"include": [], "exclude": []}, "cache_selected_only": false}}